{
  "updated": "2026-03-21T18:19:41.008834Z",
  "search_trends": [
    {
      "term": "Federal Reserve rate cut",
      "value": 1,
      "change": "+14%",
      "direction": "up"
    },
    {
      "term": "Bitcoin ETF",
      "value": 10,
      "change": "+11%",
      "direction": "up"
    },
    {
      "term": "gold price forecast",
      "value": 20,
      "change": "+36%",
      "direction": "up"
    },
    {
      "term": "recession 2026",
      "value": 14,
      "change": "+18%",
      "direction": "up"
    },
    {
      "term": "S&P 500 earnings",
      "value": 2,
      "change": "flat",
      "direction": "nt"
    }
  ],
  "market_conversations": [
    {
      "term": "Inflation / CPI narrative",
      "value": 50,
      "change": "\u2014",
      "direction": "nt"
    },
    {
      "term": "Bitcoin price action",
      "value": 50,
      "change": "\u2014",
      "direction": "nt"
    },
    {
      "term": "SEC crypto regulation",
      "value": 50,
      "change": "\u2014",
      "direction": "nt"
    },
    {
      "term": "AI stocks & semiconductors",
      "value": 50,
      "change": "\u2014",
      "direction": "nt"
    },
    {
      "term": "Geopolitical risk premium",
      "value": 50,
      "change": "\u2014",
      "direction": "nt"
    }
  ]
}